gcix/__init__.py
gcix/py.typed
gcix/_jsii/__init__.py
gcix/_jsii/gcix@v0.0.56.jsii.tgz
gcix/aws/__init__.py
gcix/container/__init__.py
gcix/git/__init__.py
gcix/gitlab/__init__.py
gcix/linux/__init__.py
gcix/python/__init__.py
gcix/security/__init__.py
gcix-0.0.56.data/scripts/cfnwaiter
gcix-0.0.56.data/scripts/gittagpep440conformity
gcix-0.0.56.dist-info/LICENSE
gcix-0.0.56.dist-info/METADATA
gcix-0.0.56.dist-info/WHEEL
gcix-0.0.56.dist-info/top_level.txt
gcix-0.0.56.dist-info/RECORD
