Metadata-Version: 2.1
Name: gcix
Version: 0.0.56
Summary: GitLab CI X Library (X stands for multilanguage)
Home-page: https://docs.gcix.dev
Author: Daniel von Essen<daniel@vonessen.eu>
License: Apache-2.0
Project-URL: Source, https://gitlab.com/gcix/gcix.git
Classifier: Intended Audience :: Developers
Classifier: Operating System :: OS Independent
Classifier: Programming Language :: JavaScript
Classifier: Programming Language :: Python :: 3 :: Only
Classifier: Programming Language :: Python :: 3.8
Classifier: Programming Language :: Python :: 3.9
Classifier: Programming Language :: Python :: 3.10
Classifier: Programming Language :: Python :: 3.11
Classifier: Typing :: Typed
Classifier: Development Status :: 5 - Production/Stable
Classifier: License :: OSI Approved
Requires-Python: ~=3.8
License-File: LICENSE
Requires-Dist: jsii <2.0.0,>=1.94.0
Requires-Dist: publication >=0.0.3
Requires-Dist: typeguard ~=2.13.3
